length-nest-pro-MQ/__init__.py
length-nest-pro-MQ/column_sort.py
length-nest-pro-MQ/day_based_rot_file_handler.py
length-nest-pro-MQ/main.py
length-nest-pro-MQ/nest_calculation_new.py
length-nest-pro-MQ/rabbitmq_manager.py
length_nest_pro_mq/__init__.py
length_nest_pro_mq/column_sort.py
length_nest_pro_mq/day_based_rot_file_handler.py
length_nest_pro_mq/main.py
length_nest_pro_mq/nest_calculation_new.py
length_nest_pro_mq/rabbitmq_manager.py
length_nest_pro_mq-0.0.5.dist-info/METADATA
length_nest_pro_mq-0.0.5.dist-info/WHEEL
length_nest_pro_mq-0.0.5.dist-info/top_level.txt
length_nest_pro_mq-0.0.5.dist-info/RECORD
