Metadata-Version: 2.1
Name: length_nest_pro_mq
Version: 0.0.5
Summary: length_nest_pro_MQ
Author: Niels Bos
Author-email: nielsb00@gmail.com
Keywords: rabbit mq,length nest pro
Requires-Dist: numpy
Requires-Dist: wheel
Requires-Dist: setuptools
Requires-Dist: pika
